Metadata-Version: 2.1
Name: WikipediaCategoryResolver
Version: 1.0.4
Summary: Named Entity Recognition using Wikipedia API
Home-page: UNKNOWN
License: UNKNOWN
Platform: UNKNOWN
